{
    "events": [
        {
            "floor": 0,
            "time": "16:00:00",
            "eventType": "suspicious",
            "description": "Человек с подозрительной улыбкой",
            "cameraId": 17,
            "location": "Кабинет 104"
        },
        {
            "floor": 1,
            "time": "16:15:00",
            "eventType": "danger",
            "description": "Падение книжной полки",
            "cameraId": 18,
            "location": "Библиотека"
        },
        {
            "floor": 2,
            "time": "16:30:00",
            "eventType": "neutral",
            "description": "Лекция по искусственному интеллекту",
            "cameraId": 19,
            "location": "Аудитория 201"
        },
        {
            "floor": 3,
            "time": "16:45:00",
            "eventType": "suspicious",
            "description": "Тень на камере",
            "cameraId": 20,
            "location": "Кабинет 302"
        },
        {
            "floor": 4,
            "time": "17:00:00",
            "eventType": "danger",
            "description": "Взрыв химического оборудования",
            "cameraId": 21,
            "location": "Кабинет 401"
        },
        {
            "floor": 0,
            "time": "17:15:00",
            "eventType": "neutral",
            "description": "Студенты устраивают пикник",
            "cameraId": 22,
            "location": "Левый коридор"
        },
        {
            "floor": 1,
            "time": "17:30:00",
            "eventType": "suspicious",
            "description": "Неопознанный объект на камере",
            "cameraId": 23,
            "location": "Кабинет 102"
        },
        {
            "floor": 2,
            "time": "17:45:00",
            "eventType": "danger",
            "description": "Вандализм на стенах",
            "cameraId": 24,
            "location": "Лестничный пролет 1 этажа"
        },
        {
            "floor": 3,
            "time": "18:00:00",
            "eventType": "neutral",
            "description": "Уборка после лекции",
            "cameraId": 25,
            "location": "Аудитория 304"
        },
        {
            "floor": 4,
            "time": "18:15:00",
            "eventType": "suspicious",
            "description": "Лицо в маске",
            "cameraId": 26,
            "location": "Лестничный пролет 3 этажа"
        },
        {
            "floor": 0,
            "time": "18:30:00",
            "eventType": "danger",
            "description": "Пожар в кабинете",
            "cameraId": 27,
            "location": "Кабинет 202"
        },
        {
            "floor": 1,
            "time": "18:45:00",
            "eventType": "neutral",
            "description": "Студенты готовят проект",
            "cameraId": 28,
            "location": "Аудитория 203"
        },
        {
            "floor": 2,
            "time": "19:00:00",
            "eventType": "suspicious",
            "description": "Необычное движение на камере",
            "cameraId": 29,
            "location": "Кабинет 301"
        },
        {
            "floor": 3,
            "time": "19:15:00",
            "eventType": "danger",
            "description": "Падение лестницы",
            "cameraId": 30,
            "location": "Лестничный пролет 2 этажа"
        },
        {
            "floor": 4,
            "time": "19:30:00",
            "eventType": "neutral",
            "description": "Презентация стартапа",
            "cameraId": 31,
            "location": "Аудитория 401"
        },
        {
            "floor": 0,
            "time": "19:45:00",
            "eventType": "suspicious",
            "description": "Человек с рюкзаком",
            "cameraId": 32,
            "location": "Лестничный пролет 3 этажа"
        },
        {
            "floor": 1,
            "time": "20:00:00",
            "eventType": "danger",
            "description": "Пожар в столовой",
            "cameraId": 33,
            "location": "Столовая"
        },
        {
            "floor": 2,
            "time": "20:15:00",
            "eventType": "neutral",
            "description": "Обеденный перерыв",
            "cameraId": 34,
            "location": "Левый коридор"
        },
        {
            "floor": 3,
            "time": "20:30:00",
            "eventType": "suspicious",
            "description": "Человек в маске и перчатках",
            "cameraId": 35,
            "location": "Кабинет 403"
        },
        {
            "floor": 4,
            "time": "20:45:00",
            "eventType": "danger",
            "description": "Химическое загрязнение",
            "cameraId": 36,
            "location": "Лестничный пролет 1 этажа"
        }
    ]
}